ducc0.cp313-win_amd64.pyd
ducc0-0.40.0.dist-info/METADATA
ducc0-0.40.0.dist-info/WHEEL
ducc0-0.40.0.dist-info/licenses/LICENSE
ducc0-0.40.0.dist-info/RECORD
