Metadata-Version: 2.1
Name: ducc0
Version: 0.40.0
Summary: Distinctly useful code collection: contains efficient algorithms for Fast Fourier (and related) transforms, spherical harmonic transforms involving very general spherical grids, gridding/degridding tools for radio interferometry, 4pi spherical convolution operators and much more.
Author-Email: Martin Reinecke <martin@mpa-garching.mpg.de>
License:                     GNU GENERAL PUBLIC LICENSE
Classifier: Development Status :: 5 - Production/Stable
Classifier: Intended Audience :: Science/Research
Classifier: Topic :: Scientific/Engineering :: Mathematics
Classifier: Topic :: Scientific/Engineering :: Physics
Classifier: License :: OSI Approved :: GNU General Public License v2 or later (GPLv2+)
Classifier: Operating System :: OS Independent
Classifier: Programming Language :: C++
Classifier: Programming Language :: Python
Requires-Python: >=3.8
Requires-Dist: numpy>=1.17.0
